deefuse/__init__.py
deefuse/__main__.py
deefuse/config.py
deefuse/csv_handler.py
deefuse/deezer_api.py
deefuse/downloader.py
deefuse/utils.py
deefuse/ui/__init__.py
deefuse/ui/main_window.py
deefuse/ui/progress_dialog.py
deefuse-0.2.5.dist-info/licenses/LICENSE
deefuse-0.2.5.dist-info/METADATA
deefuse-0.2.5.dist-info/WHEEL
deefuse-0.2.5.dist-info/entry_points.txt
deefuse-0.2.5.dist-info/top_level.txt
deefuse-0.2.5.dist-info/RECORD
