Metadata-Version: 2.4
Name: deefuse
Version: 0.2.5
Summary: Deemix library upgrader, automatically matching local files
Author-email: Mitchell Winter <mitchell.winter@queensu.ca>
License: MIT License
Classifier: License :: OSI Approved :: MIT License
Classifier: Programming Language :: Python :: 3
Classifier: Environment :: Win32 (MS Windows)
Classifier: Environment :: MacOS X
Classifier: Environment :: X11 Applications
Classifier: Topic :: Multimedia :: Sound/Audio :: Players
Requires-Python: >=3.9
License-File: LICENSE
Requires-Dist: customtkinter>=5.1
Requires-Dist: mutagen>=1.47
Requires-Dist: requests>=2.31
Provides-Extra: dev
Requires-Dist: pyinstaller>=6.0; extra == "dev"
Requires-Dist: build; extra == "dev"
Dynamic: license-file
